pubs/plugs/extract/__init__.py
pubs/plugs/extract/annotation.py
pubs/plugs/extract/extract.py
pubs_extract-0.2.0.dist-info/METADATA
pubs_extract-0.2.0.dist-info/WHEEL
pubs_extract-0.2.0.dist-info/RECORD
