Metadata-Version: 2.1
Name: pubs-extract
Version: 0.2.0
Summary: A pdf annotation extraction plugin for pubs bibliography manager
License: LGPL-3.0
Author: Marty Oehme
Author-email: marty.oehme@gmail.com
Requires-Python: >=3.10,<4.0
Classifier: License :: OSI Approved :: GNU Lesser General Public License v3 (LGPLv3)
Classifier: Programming Language :: Python :: 3
Classifier: Programming Language :: Python :: 3.10
Classifier: Programming Language :: Python :: 3.11
Requires-Dist: levenshtein (>=0.20.8,<0.21.0)
Requires-Dist: pymupdf (>=1.21.1,<2.0.0)
